multiway_alignment/__init__.py
multiway_alignment/consensus.py
multiway_alignment/null_models.py
multiway_alignment/score.py
multiway_alignment/visualizations.py
multiway_alignment/data/__init__.py
multiway_alignment/data/anes.py
multiway_alignment/data/finnish_parliament.py
multiway_alignment/data/finnish_twitter.py
multiway_alignment/data/usa.py
multiway_alignment/utils/__init__.py
multiway_alignment/utils/logging.py
tests/__init__.py
tests/test_get_consensus_labels.py
tests/test_get_consensus_labels_df.py
tests/test_get_consensus_partition.py
tests/test_get_consensus_partition_recursive.py
tests/test_maximal_alignment_curve.py
tests/test_maximal_alignment_curve_full.py
tests/test_multiway_alignment_score.py
tests/test_multiway_alignment_score_full.py
multiway_alignment-0.0.2.dist-info/LICENSE
multiway_alignment-0.0.2.dist-info/METADATA
multiway_alignment-0.0.2.dist-info/WHEEL
multiway_alignment-0.0.2.dist-info/top_level.txt
multiway_alignment-0.0.2.dist-info/RECORD
