Metadata-Version: 2.1
Name: multiway_alignment
Version: 0.0.2
Summary: Quantifying multiway (higher-order) alignment with mutual information
Home-page: https://github.com/letiziaia/multiway-alignment
Author: Letizia Iannucci
Author-email: letizia.iannucci@aalto.fi
License: Apache 2.0
Classifier: Development Status :: 3 - Alpha
Classifier: Intended Audience :: Science/Research
Classifier: License :: OSI Approved :: Apache Software License
Classifier: Programming Language :: Python :: 3
Classifier: Programming Language :: Python :: 3.10
Classifier: Programming Language :: Python :: 3.11
Classifier: Programming Language :: Python :: 3.12
Classifier: Programming Language :: Python :: 3.13
License-File: LICENSE
Requires-Dist: click
Requires-Dist: joblib
Requires-Dist: loguru
Requires-Dist: matplotlib
Requires-Dist: networkx
Requires-Dist: numpy
Requires-Dist: pandas
Requires-Dist: scikit-learn
Requires-Dist: scipy
Requires-Dist: seaborn
Requires-Dist: tqdm
